libraw/__init__.py
libraw/bindings.py
libraw/callbacks.py
libraw/errors.py
libraw/structs_16.py
libraw/structs_17.py
libraw/structs_18.py
rawkit/__init__.py
rawkit/errors.py
rawkit/metadata.py
rawkit/options.py
rawkit/raw.py
rawkit/util.py
rawkit-0.6.0.dist-info/DESCRIPTION.rst
rawkit-0.6.0.dist-info/METADATA
rawkit-0.6.0.dist-info/RECORD
rawkit-0.6.0.dist-info/WHEEL
rawkit-0.6.0.dist-info/metadata.json
rawkit-0.6.0.dist-info/top_level.txt
