Metadata-Version: 1.1
Name: rawkit
Version: 0.6.0
Summary: CTypes based LibRaw bindings
Home-page: https://rawkit.readthedocs.org
Author: Cameron Paul, Sam Whited
Author-email: sam@samwhited.com
License: UNKNOWN
Keywords: encoding,images,photography,libraw,raw,photos
Platform: UNKNOWN
Classifier: Programming Language :: Python
Classifier: Programming Language :: Python :: 2
Classifier: Programming Language :: Python :: 2.7
Classifier: Programming Language :: Python :: 3
Classifier: Programming Language :: Python :: 3.3
Classifier: Programming Language :: Python :: 3.4
Classifier: Programming Language :: Python :: Implementation :: PyPy
Classifier: Development Status :: 3 - Alpha
Classifier: Intended Audience :: Developers
Classifier: License :: OSI Approved :: MIT License
Classifier: Operating System :: OS Independent
Classifier: Topic :: Software Development :: Libraries :: Python Modules
